odoo9_addon_cmis-9.0.1.0.0.99.dev8-py2.7-nspkg.pth
odoo9_addon_cmis-9.0.1.0.0.99.dev8.dist-info/METADATA
odoo9_addon_cmis-9.0.1.0.0.99.dev8.dist-info/RECORD
odoo9_addon_cmis-9.0.1.0.0.99.dev8.dist-info/WHEEL
odoo9_addon_cmis-9.0.1.0.0.99.dev8.dist-info/namespace_packages.txt
odoo9_addon_cmis-9.0.1.0.0.99.dev8.dist-info/top_level.txt
odoo_addons/cmis/README.rst
odoo_addons/cmis/__init__.py
odoo_addons/cmis/__openerp__.py
odoo_addons/cmis/exceptions.py
odoo_addons/cmis/demo/cmis_backend_demo.xml
odoo_addons/cmis/i18n/cmis.pot
odoo_addons/cmis/i18n/fr.po
odoo_addons/cmis/models/__init__.py
odoo_addons/cmis/models/cmis_backend.py
odoo_addons/cmis/security/cmis_backend.xml
odoo_addons/cmis/static/description/icon.png
odoo_addons/cmis/static/src/img/icon.png
odoo_addons/cmis/tests/__init__.py
odoo_addons/cmis/tests/test_cmis_backend.py
odoo_addons/cmis/views/cmis_backend.xml
odoo_addons/cmis/views/cmis_menu.xml
