Metadata-Version: 2.1
Name: odoo9-addon-cmis
Version: 9.0.1.0.0.99.dev8
Summary: Connect OpenERP with a CMIS server
Home-page: https://odoo-community.org/
Author: Savoir-faire Linux, ACSONE SA/NV, Odoo Community Association (OCA)
Author-email: support@odoo-community.org
License: AGPL-3
Platform: UNKNOWN
Classifier: Programming Language :: Python
Classifier: Framework :: Odoo
Classifier: License :: OSI Approved :: GNU Affero General Public License v3
Requires-Python: ~=2.7
Requires-Dist: cmislib
Requires-Dist: odoo (<9.1a,>=9.0a)
